{"title":"maxthon","uid":7494273,"size":24466528,"categoryP":"applications","categoryS":"windows","magnet":"?xt=urn:btih:119401bf510fb6e383c27e3d0ec311a24cad5f5e&amp;dn=maxthon&amp;tr=udp%3A%2F%2Ftracker.openbittorrent.com%3A80&amp;tr=udp%3A%2F%2Fopen.demonii.com%3A1337&amp;tr=udp%3A%2F%2Ftracker.coppersurfer.tk%3A6969&amp;tr=udp%3A%2F%2Fexodus.desync.com%3A6969","seeders":0,"leechers":1,"uploader":"Ahed91","files":1,"time":1343833695,"description":"good","torrent":{"xt":"urn:btih:119401bf510fb6e383c27e3d0ec311a24cad5f5e","amp;dn":"maxthon","amp;tr":["udp%3A%2F%2Ftracker.openbittorrent.com%3A80","udp%3A%2F%2Fopen.demonii.com%3A1337","udp%3A%2F%2Ftracker.coppersurfer.tk%3A6969","udp%3A%2F%2Fexodus.desync.com%3A6969"],"infoHash":"119401bf510fb6e383c27e3d0ec311a24cad5f5e","infoHashBuffer":{"type":"Buffer","data":[17,148,1,191,81,15,182,227,131,194,126,61,14,195,17,162,76,173,95,94]},"announce":[],"urlList":[]}}