{"title":"The.Dictator.2012.UNRATED.BDRip.XviD-AMIABLE","uid":7533983,"size":733908992,"categoryP":"video","categoryS":"movies","magnet":"?xt=urn:btih:26378e60cfd507f58bfdefdc07a143a2ad844c8c&amp;dn=The.Dictator.2012.UNRATED.BDRip.XviD-AMIABLE&amp;tr=udp%3A%2F%2Ftracker.openbittorrent.com%3A80&amp;tr=udp%3A%2F%2Fopen.demonii.com%3A1337&amp;tr=udp%3A%2F%2Ftracker.coppersurfer.tk%3A6969&amp;tr=udp%3A%2F%2Fexodus.desync.com%3A6969","seeders":0,"leechers":0,"uploader":"EzioArmend","files":1,"time":1345042334,"description":"The.Dictator.2012.UNRATED.BDRip.XviD-AMIABLE\n\n\nScreenshot:  &lt;a href=&quot;\nhttp://bayimg.com/laBLGaaEC&quot; rel=&quot;nofollow&quot; target=&quot;_NEW&quot;&gt;\nhttp://bayimg.com/laBLGaaEC&lt;/a&gt;\n\n700MB\n\nEnjoy! ","torrent":{"xt":"urn:btih:26378e60cfd507f58bfdefdc07a143a2ad844c8c","amp;dn":"The.Dictator.2012.UNRATED.BDRip.XviD-AMIABLE","amp;tr":["udp%3A%2F%2Ftracker.openbittorrent.com%3A80","udp%3A%2F%2Fopen.demonii.com%3A1337","udp%3A%2F%2Ftracker.coppersurfer.tk%3A6969","udp%3A%2F%2Fexodus.desync.com%3A6969"],"infoHash":"26378e60cfd507f58bfdefdc07a143a2ad844c8c","infoHashBuffer":{"type":"Buffer","data":[38,55,142,96,207,213,7,245,139,253,239,220,7,161,67,162,173,132,76,140]},"announce":[],"urlList":[]}}