{"title":"History Ch Modern Marvels 4of6 Trans Siberian Railway XviD AC3 ","uid":7581062,"size":735156224,"categoryP":"video","categoryS":"tv_shows","magnet":"?xt=urn:btih:6615053e8dea4a8f9b4ddcdfc67a738b97c1be5e&amp;dn=History+Ch+Modern+Marvels+4of6+Trans+Siberian+Railway+XviD+AC3+&amp;tr=udp%3A%2F%2Ftracker.openbittorrent.com%3A80&amp;tr=udp%3A%2F%2Fopen.demonii.com%3A1337&amp;tr=udp%3A%2F%2Ftracker.coppersurfer.tk%3A6969&amp;tr=udp%3A%2F%2Fexodus.desync.com%3A6969","seeders":0,"leechers":1,"uploader":"MVGroup","files":-1,"time":1346246433,"description":"Modern Marvels\n\nHistory, Technology Documentary hosted by Bruce Nash, published by History Channel in 2002 - English narration\n\n\nInformation\n------------------------------\n\nModern Marvels\nCelebrating modern engineering excellence. This programme journeys back in time to take a look at some of the world's most incredible architectural masterpieces of all time, including marvels of staggering proportions. Hadrian's Wall, which stretches 74 miles long and is 2,000 years old, a tantalising treasure that historians are eager to explore further. London's Tower Bridge, a symbol of industrial might and technological daring. Gustave's Eiffel Tower, the very essence of Paris. San Francisco's Golden Gate Bridge, which fifty years after its construction is still regarded as one of the world's most incredible engineering accomplishments. One of the world's most ambitious engineering projects The Trans-Siberian Railway and the Empire State Building, synonymous with its home New York City.\n\n\n\n4)  Trans Siberian Railway \nStretching nearly 6,000 miles from Moscow to Vladivostok, the Trans-Siberian Railroad was one of the most ambitious engineering projects ever undertaken. Started in 1891 on the orders of Czar Alexander III, it is the longest, most expensive and most complicated railroad ever built. Amazingly this phenomenal railroad was completed in less than 15 years, despite having to cross vast stretches of the most remote and unforgiving land on earth.\n\n\nScreenshots\n------------------------------ &lt;a href=&quot;\nhttp://img687.imageshack.us/img687/1662/modernmarvelsscreen0.jpg&quot; rel=&quot;nofollow&quot; target=&quot;_NEW&quot;&gt;\nhttp://img687.imageshack.us/img687/1662/modernmarvelsscreen0.jpg&lt;/a&gt; &lt;a href=&quot;\nhttp://img850.imageshack.us/img850/4788/modernmarvelsscreen1.jpg&quot; rel=&quot;nofollow&quot; target=&quot;_NEW&quot;&gt;\nhttp://img850.imageshack.us/img850/4788/modernmarvelsscreen1.jpg&lt;/a&gt; &lt;a href=&quot;\nhttp://img442.imageshack.us/img442/1277/modernmarvelsscreen2.jpg&quot; rel=&quot;nofollow&quot; target=&quot;_NEW&quot;&gt;\nhttp://img442.imageshack.us/img442/1277/modernmarvelsscreen2.jpg&lt;/a&gt; &lt;a href=&quot;\nhttp://img267.imageshack.us/img267/4800/modernmarvelsscreen3.jpg&quot; rel=&quot;nofollow&quot; target=&quot;_NEW&quot;&gt;\nhttp://img267.imageshack.us/img267/4800/modernmarvelsscreen3.jpg&lt;/a&gt; &lt;a href=&quot;\nhttp://img833.imageshack.us/img833/8073/modernmarvelsscreen4.jpg&quot; rel=&quot;nofollow&quot; target=&quot;_NEW&quot;&gt;\nhttp://img833.imageshack.us/img833/8073/modernmarvelsscreen4.jpg&lt;/a&gt; &lt;a href=&quot;\nhttp://img525.imageshack.us/img525/7781/modernmarvelsscreen5.jpg&quot; rel=&quot;nofollow&quot; target=&quot;_NEW&quot;&gt;\nhttp://img525.imageshack.us/img525/7781/modernmarvelsscreen5.jpg&lt;/a&gt; &lt;a href=&quot;\nhttp://img404.imageshack.us/img404/7879/modernmarvelsscreen6.jpg&quot; rel=&quot;nofollow&quot; target=&quot;_NEW&quot;&gt;\nhttp://img404.imageshack.us/img404/7879/modernmarvelsscreen6.jpg&lt;/a&gt; &lt;a href=&quot;\nhttp://img138.imageshack.us/img138/6919/modernmarvelsscreen7.jpg&quot; rel=&quot;nofollow&quot; target=&quot;_NEW&quot;&gt;\nhttp://img138.imageshack.us/img138/6919/modernmarvelsscreen7.jpg&lt;/a&gt; &lt;a href=&quot;\nhttp://img849.imageshack.us/img849/1181/modernmarvelsscreen8.jpg&quot; rel=&quot;nofollow&quot; target=&quot;_NEW&quot;&gt;\nhttp://img849.imageshack.us/img849/1181/modernmarvelsscreen8.jpg&lt;/a&gt; &lt;a href=&quot;\nhttp://img253.imageshack.us/img253/4668/modernmarvelsscreen9.jpg&quot; rel=&quot;nofollow&quot; target=&quot;_NEW&quot;&gt;\nhttp://img253.imageshack.us/img253/4668/modernmarvelsscreen9.jpg&lt;/a&gt; &lt;a href=&quot;\nhttp://img411.imageshack.us/img411/6057/modernmarvelsscreen10f.jpg&quot; rel=&quot;nofollow&quot; target=&quot;_NEW&quot;&gt;\nhttp://img411.imageshack.us/img411/6057/modernmarvelsscreen10f.jpg&lt;/a&gt; &lt;a href=&quot;\nhttp://img14.imageshack.us/img14/5092/modernmarvelsscreen11.jpg&quot; rel=&quot;nofollow&quot; target=&quot;_NEW&quot;&gt;\nhttp://img14.imageshack.us/img14/5092/modernmarvelsscreen11.jpg&lt;/a&gt; \n\nTechnical Specs\n------------------------------\n\n\n * Video Codec: XviD ISO MPEG-4\n * Video Bitrate: 2032 kbps\n * Video Resolution: 720 x 528\n * Video Aspect Ratio: (4:3)\n * Frames Per Second: 25\n * Audio Codec: 0x2000 (Dolby AC3)\n * Audio Bitrate: 128 kb/s AC3 48000 Hz\n * Audio Streams: 2\n * Audio Languages: English\n * RunTime Per Part: 45.Mins\n * Number Of Parts: 6\n * Part Size: 700 MB\n * Source: DVD\n * Encoded by: Harry65\n\n\n\nLinks\n------------------------------\n\n1)  Further Information &lt;a href=&quot;\nhttp://en.wikipedia.org/wiki/Hadrian%27s_Wall&quot; rel=&quot;nofollow&quot; target=&quot;_NEW&quot;&gt;\nhttp://en.wikipedia.org/wiki/Hadrian%27s_Wall&lt;/a&gt; &lt;a href=&quot;\nhttp://en.wikipedia.org/wiki/Tower_Bridge&quot; rel=&quot;nofollow&quot; target=&quot;_NEW&quot;&gt;\nhttp://en.wikipedia.org/wiki/Tower_Bridge&lt;/a&gt; &lt;a href=&quot;\nhttp://en.wikipedia.org/wiki/Eiffel_Tower&quot; rel=&quot;nofollow&quot; target=&quot;_NEW&quot;&gt;\nhttp://en.wikipedia.org/wiki/Eiffel_Tower&lt;/a&gt; &lt;a href=&quot;\nhttp://en.wikipedia.org/wiki/Trans-Siberian_Railway&quot; rel=&quot;nofollow&quot; target=&quot;_NEW&quot;&gt;\nhttp://en.wikipedia.org/wiki/Trans-Siberian_Railway&lt;/a&gt; &lt;a href=&quot;\nhttp://en.wikipedia.org/wiki/Empire_State_Building&quot; rel=&quot;nofollow&quot; target=&quot;_NEW&quot;&gt;\nhttp://en.wikipedia.org/wiki/Empire_State_Building&lt;/a&gt; &lt;a href=&quot;\nhttp://en.wikipedia.org/wiki/Golden_Gate_Bridge&quot; rel=&quot;nofollow&quot; target=&quot;_NEW&quot;&gt;\nhttp://en.wikipedia.org/wiki/Golden_Gate_Bridge&lt;/a&gt;\n\n","torrent":{"xt":"urn:btih:6615053e8dea4a8f9b4ddcdfc67a738b97c1be5e","amp;dn":"History+Ch+Modern+Marvels+4of6+Trans+Siberian+Railway+XviD+AC3+","amp;tr":["udp%3A%2F%2Ftracker.openbittorrent.com%3A80","udp%3A%2F%2Fopen.demonii.com%3A1337","udp%3A%2F%2Ftracker.coppersurfer.tk%3A6969","udp%3A%2F%2Fexodus.desync.com%3A6969"],"infoHash":"6615053e8dea4a8f9b4ddcdfc67a738b97c1be5e","infoHashBuffer":{"type":"Buffer","data":[102,21,5,62,141,234,74,143,155,77,220,223,198,122,115,139,151,193,190,94]},"announce":[],"urlList":[]}}