{"title":"(1997) Grand Theft Auto 3DFX - MacOS X |Full/Warped| APP |","uid":7104664,"size":777303331,"categoryP":"games","categoryS":"mac","magnet":"?xt=urn:btih:6e8d0a5c8b5791e76de511dc853aa8711b0429db&amp;dn=%281997%29+Grand+Theft+Auto+3DFX+-+MacOS+X+%7CFull%2FWarped%7C+APP+%7C&amp;tr=udp%3A%2F%2Ftracker.openbittorrent.com%3A80&amp;tr=udp%3A%2F%2Fopen.demonii.com%3A1337&amp;tr=udp%3A%2F%2Ftracker.coppersurfer.tk%3A6969&amp;tr=udp%3A%2F%2Fexodus.desync.com%3A6969","seeders":0,"leechers":1,"uploader":"shadowmajk","files":-1,"time":1331826956,"description":"Full warped classic Grand Theft Auto (1997) with radio and 3dfx/glide graphic inside .app for MacOS X.\n\nSimply drag&amp;drop to install and play.\n\nTested on Apple Snow Leopard 10.6.8 MP3.1 8800GT.\n\n~GTAOSX 0.9v","torrent":{"xt":"urn:btih:6e8d0a5c8b5791e76de511dc853aa8711b0429db","amp;dn":"%281997%29+Grand+Theft+Auto+3DFX+-+MacOS+X+%7CFull%2FWarped%7C+APP+%7C","amp;tr":["udp%3A%2F%2Ftracker.openbittorrent.com%3A80","udp%3A%2F%2Fopen.demonii.com%3A1337","udp%3A%2F%2Ftracker.coppersurfer.tk%3A6969","udp%3A%2F%2Fexodus.desync.com%3A6969"],"infoHash":"6e8d0a5c8b5791e76de511dc853aa8711b0429db","infoHashBuffer":{"type":"Buffer","data":[110,141,10,92,139,87,145,231,109,229,17,220,133,58,168,113,27,4,41,219]},"announce":[],"urlList":[]}}