{"title":"Breaking.Bad.S05E07.720p.HDTV.x264-COMPULSiON [PublicHD]","uid":7573057,"size":1369904044,"categoryP":"video","categoryS":"hd___tv_shows","magnet":"?xt=urn:btih:722bb56a3592ed38f70b2105b646a2bec07822a5&amp;dn=Breaking.Bad.S05E07.720p.HDTV.x264-COMPULSiON+%5BPublicHD%5D&amp;tr=udp%3A%2F%2Ftracker.openbittorrent.com%3A80&amp;tr=udp%3A%2F%2Fopen.demonii.com%3A1337&amp;tr=udp%3A%2F%2Ftracker.coppersurfer.tk%3A6969&amp;tr=udp%3A%2F%2Fexodus.desync.com%3A6969","seeders":0,"leechers":0,"uploader":"DibyaTPB","files":3,"time":1346044595,"description":"PublicHD - High-Definition Bittorrent Community \n\n &lt;a href=&quot; https://publichd.eu&quot; rel=&quot;nofollow&quot; target=&quot;_NEW&quot;&gt; https://publichd.eu&lt;/a&gt; \n\n ----------------------------------------- \nRELEASE: Breaking.Bad.S05E07.720p.HDTV.x264-COMPULSiON\nDATE: 2012-08-27\n\n","torrent":{"xt":"urn:btih:722bb56a3592ed38f70b2105b646a2bec07822a5","amp;dn":"Breaking.Bad.S05E07.720p.HDTV.x264-COMPULSiON+%5BPublicHD%5D","amp;tr":["udp%3A%2F%2Ftracker.openbittorrent.com%3A80","udp%3A%2F%2Fopen.demonii.com%3A1337","udp%3A%2F%2Ftracker.coppersurfer.tk%3A6969","udp%3A%2F%2Fexodus.desync.com%3A6969"],"infoHash":"722bb56a3592ed38f70b2105b646a2bec07822a5","infoHashBuffer":{"type":"Buffer","data":[114,43,181,106,53,146,237,56,247,11,33,5,182,70,162,190,192,120,34,165]},"announce":[],"urlList":[]}}