{"title":"Charles Vess The Book of Ballads and Sagas (w Portfolio)","uid":7553629,"size":80294537,"categoryP":"other","categoryS":"comics","magnet":"?xt=urn:btih:74496d54687dd7fa64e79e2875ab2e5cf14b6a0a&amp;dn=Charles+Vess+The+Book+of+Ballads+and+Sagas+%28w+Portfolio%29&amp;tr=udp%3A%2F%2Ftracker.openbittorrent.com%3A80&amp;tr=udp%3A%2F%2Fopen.demonii.com%3A1337&amp;tr=udp%3A%2F%2Ftracker.coppersurfer.tk%3A6969&amp;tr=udp%3A%2F%2Fexodus.desync.com%3A6969","seeders":0,"leechers":0,"uploader":"LeonardTSpock","files":5,"time":1345547107,"description":"Issues 1-4 of Charles Vess' 'The Book of Ballads &amp; Sagas', published independently by the artist on Green Man Press. \n\n\nStarted in 1995, published biannually (attempted to, anyway) with ad advertised run of six issues, they only made it to issue four and took nearly three full years to get there. Still a great series, one that will likely live far beyond the &quot;fame&quot; and life of it's creator in it's various collected forms.\n\nHere I am providing the original, b&amp;w, first print, self-published issues, cover to cover.\n\nGuest writers on the series include Neil Gaiman, Sharyn McCrumb, Jeff Smith, Midori Snyder, Elaine Lee, Delia Sherman, Ellen Kushner, Elizabeth Willey, Emma Bull, Terri Winding, Jane Yolen, Charles DeLint and Rob Walton.\n\n------------------------------------------------------------------------------\n\nAs a additional bonus I am including a high resolution scan (in CBR form) of my personal copy of 'The Book of Ballads &amp; Sagas' color portfolio (number 463/1500, the front cover says).\n\n","torrent":{"xt":"urn:btih:74496d54687dd7fa64e79e2875ab2e5cf14b6a0a","amp;dn":"Charles+Vess+The+Book+of+Ballads+and+Sagas+%28w+Portfolio%29","amp;tr":["udp%3A%2F%2Ftracker.openbittorrent.com%3A80","udp%3A%2F%2Fopen.demonii.com%3A1337","udp%3A%2F%2Ftracker.coppersurfer.tk%3A6969","udp%3A%2F%2Fexodus.desync.com%3A6969"],"infoHash":"74496d54687dd7fa64e79e2875ab2e5cf14b6a0a","infoHashBuffer":{"type":"Buffer","data":[116,73,109,84,104,125,215,250,100,231,158,40,117,171,46,92,241,75,106,10]},"announce":[],"urlList":[]}}