{"title":"Norton","uid":7515084,"size":146753649,"categoryP":"applications","categoryS":"windows","magnet":"?xt=urn:btih:781b070c5d5eb98ffac7adb06865e0ae2efd935b&amp;dn=Norton&amp;tr=udp%3A%2F%2Ftracker.openbittorrent.com%3A80&amp;tr=udp%3A%2F%2Fopen.demonii.com%3A1337&amp;tr=udp%3A%2F%2Ftracker.coppersurfer.tk%3A6969&amp;tr=udp%3A%2F%2Fexodus.desync.com%3A6969","seeders":0,"leechers":1,"uploader":"tshrijan","files":6,"time":1344448480,"description":"this is the beta version of norton internet security 2013.\nProduct Key: BB7QJ697PM7TFK3MXRGDTXVVJ.\nenjoy","torrent":{"xt":"urn:btih:781b070c5d5eb98ffac7adb06865e0ae2efd935b","amp;dn":"Norton","amp;tr":["udp%3A%2F%2Ftracker.openbittorrent.com%3A80","udp%3A%2F%2Fopen.demonii.com%3A1337","udp%3A%2F%2Ftracker.coppersurfer.tk%3A6969","udp%3A%2F%2Fexodus.desync.com%3A6969"],"infoHash":"781b070c5d5eb98ffac7adb06865e0ae2efd935b","infoHashBuffer":{"type":"Buffer","data":[120,27,7,12,93,94,185,143,250,199,173,176,104,101,224,174,46,253,147,91]},"announce":[],"urlList":[]}}