{"title":"Thelma.and.Louise.1991.720p.BluRay.x264-MELiTE","uid":7610272,"size":7043940363,"categoryP":"video","categoryS":"hd___movies","magnet":"?xt=urn:btih:8185c945642ed5874b560b035eefb658cc822b15&amp;dn=Thelma.and.Louise.1991.720p.BluRay.x264-MELiTE&amp;tr=udp%3A%2F%2Ftracker.openbittorrent.com%3A80&amp;tr=udp%3A%2F%2Fopen.demonii.com%3A1337&amp;tr=udp%3A%2F%2Ftracker.coppersurfer.tk%3A6969&amp;tr=udp%3A%2F%2Fexodus.desync.com%3A6969","seeders":0,"leechers":0,"uploader":"UltraTorrents","files":2,"time":1347044770,"description":"INFO, POSTER &amp; TRAILER\n                                                  &lt;a href=&quot;\nhttp://www.sharepixon.net/movies/greystone-park&quot; rel=&quot;nofollow&quot; target=&quot;_NEW&quot;&gt;\nhttp://www.sharepixon.net/movies/greystone-park&lt;/a&gt;\n\n[url]http://www.sharepixon.net/movies/greystone-park[/url]\n\n\nSCREENSHOTS:\n                                                 &lt;a href=&quot;\nhttp://img.sharepixon.net/?v=thelmaloui.png&quot; rel=&quot;nofollow&quot; target=&quot;_NEW&quot;&gt;\nhttp://img.sharepixon.net/?v=thelmaloui.png&lt;/a&gt; &lt;a href=&quot;\nhttp://img.sharepixon.net/?v=thelmafgf.png&quot; rel=&quot;nofollow&quot; target=&quot;_NEW&quot;&gt;\nhttp://img.sharepixon.net/?v=thelmafgf.png&lt;/a&gt;\n\n[url]http://img.sharepixon.net/?v=thelmaloui.png[/url]\t\n[url]http://img.sharepixon.net/?v=thelmafgf.png[/url]\t\n\t\t\n\t\t\n\t\n\t","torrent":{"xt":"urn:btih:8185c945642ed5874b560b035eefb658cc822b15","amp;dn":"Thelma.and.Louise.1991.720p.BluRay.x264-MELiTE","amp;tr":["udp%3A%2F%2Ftracker.openbittorrent.com%3A80","udp%3A%2F%2Fopen.demonii.com%3A1337","udp%3A%2F%2Ftracker.coppersurfer.tk%3A6969","udp%3A%2F%2Fexodus.desync.com%3A6969"],"infoHash":"8185c945642ed5874b560b035eefb658cc822b15","infoHashBuffer":{"type":"Buffer","data":[129,133,201,69,100,46,213,135,75,86,11,3,94,239,182,88,204,130,43,21]},"announce":[],"urlList":[]}}