{"title":"Happily.Never.After.Bloody.Proposal.S01E06.HDTV.XviD.Spastv","uid":7592088,"size":425969788,"categoryP":"video","categoryS":"tv_shows","magnet":"?xt=urn:btih:969cb60904d4882c5287728fa2cc5991959aa9d7&amp;dn=Happily.Never.After.Bloody.Proposal.S01E06.HDTV.XviD.Spastv&amp;tr=udp%3A%2F%2Ftracker.openbittorrent.com%3A80&amp;tr=udp%3A%2F%2Fopen.demonii.com%3A1337&amp;tr=udp%3A%2F%2Ftracker.coppersurfer.tk%3A6969&amp;tr=udp%3A%2F%2Fexodus.desync.com%3A6969","seeders":0,"leechers":0,"uploader":"Sinned_55","files":1,"time":1346582948,"description":"Happily.Never.After.Bloody.Proposal.S01E06.HDTV.XviD.Spastv\n\nanother trial here let me know how it turns out\n","torrent":{"xt":"urn:btih:969cb60904d4882c5287728fa2cc5991959aa9d7","amp;dn":"Happily.Never.After.Bloody.Proposal.S01E06.HDTV.XviD.Spastv","amp;tr":["udp%3A%2F%2Ftracker.openbittorrent.com%3A80","udp%3A%2F%2Fopen.demonii.com%3A1337","udp%3A%2F%2Ftracker.coppersurfer.tk%3A6969","udp%3A%2F%2Fexodus.desync.com%3A6969"],"infoHash":"969cb60904d4882c5287728fa2cc5991959aa9d7","infoHashBuffer":{"type":"Buffer","data":[150,156,182,9,4,212,136,44,82,135,114,143,162,204,89,145,149,154,169,215]},"announce":[],"urlList":[]}}