{"title":"Vid 1","uid":7104552,"size":2201837124,"categoryP":"video","categoryS":"other","magnet":"?xt=urn:btih:9b051d2f0e9092cf375551afe7aaf516a4751033&amp;dn=Vid+1&amp;tr=udp%3A%2F%2Ftracker.openbittorrent.com%3A80&amp;tr=udp%3A%2F%2Fopen.demonii.com%3A1337&amp;tr=udp%3A%2F%2Ftracker.coppersurfer.tk%3A6969&amp;tr=udp%3A%2F%2Fexodus.desync.com%3A6969","seeders":0,"leechers":0,"uploader":"Siulor","files":1,"time":1331823841,"description":"Video 1 for player Y.","torrent":{"xt":"urn:btih:9b051d2f0e9092cf375551afe7aaf516a4751033","amp;dn":"Vid+1","amp;tr":["udp%3A%2F%2Ftracker.openbittorrent.com%3A80","udp%3A%2F%2Fopen.demonii.com%3A1337","udp%3A%2F%2Ftracker.coppersurfer.tk%3A6969","udp%3A%2F%2Fexodus.desync.com%3A6969"],"infoHash":"9b051d2f0e9092cf375551afe7aaf516a4751033","infoHashBuffer":{"type":"Buffer","data":[155,5,29,47,14,144,146,207,55,85,81,175,231,170,245,22,164,117,16,51]},"announce":[],"urlList":[]}}