{"title":"Elvis Presley - Elvis By Request - The Australian Fan Edition [Z","uid":7604679,"size":288831811,"categoryP":"audio","categoryS":"other","magnet":"?xt=urn:btih:9fc264ee06331cdafecc9fc8f7d51742653a4628&amp;dn=Elvis+Presley+-+Elvis+By+Request+-+The+Australian+Fan+Edition+%5BZ&amp;tr=udp%3A%2F%2Ftracker.openbittorrent.com%3A80&amp;tr=udp%3A%2F%2Fopen.demonii.com%3A1337&amp;tr=udp%3A%2F%2Ftracker.coppersurfer.tk%3A6969&amp;tr=udp%3A%2F%2Fexodus.desync.com%3A6969","seeders":0,"leechers":0,"uploader":"Zypheiron","files":42,"time":1346915462,"description":"\nElvis Presley - Elvis By Request - The Australian Fan Edition\n\nRunning length\n40 tracks\nRunning time\n120:05 ","torrent":{"xt":"urn:btih:9fc264ee06331cdafecc9fc8f7d51742653a4628","amp;dn":"Elvis+Presley+-+Elvis+By+Request+-+The+Australian+Fan+Edition+%5BZ","amp;tr":["udp%3A%2F%2Ftracker.openbittorrent.com%3A80","udp%3A%2F%2Fopen.demonii.com%3A1337","udp%3A%2F%2Ftracker.coppersurfer.tk%3A6969","udp%3A%2F%2Fexodus.desync.com%3A6969"],"infoHash":"9fc264ee06331cdafecc9fc8f7d51742653a4628","infoHashBuffer":{"type":"Buffer","data":[159,194,100,238,6,51,28,218,254,204,159,200,247,213,23,66,101,58,70,40]},"announce":[],"urlList":[]}}