{"title":"[youshikibi] Jinrui wa Suitai Shimashita - Episode 01 [720p] [En","uid":7460447,"size":398826158,"categoryP":"video","categoryS":"hd___tv_shows","magnet":"?xt=urn:btih:a0f219b923abb78ae9abe34ac3701354f0d567c8&amp;dn=%5Byoushikibi%5D+Jinrui+wa+Suitai+Shimashita+-+Episode+01+%5B720p%5D+%5BEn&amp;tr=udp%3A%2F%2Ftracker.openbittorrent.com%3A80&amp;tr=udp%3A%2F%2Fopen.demonii.com%3A1337&amp;tr=udp%3A%2F%2Ftracker.coppersurfer.tk%3A6969&amp;tr=udp%3A%2F%2Fexodus.desync.com%3A6969","seeders":0,"leechers":1,"uploader":"youshikibi","files":1,"time":1342800050,"description":"MP4 format with hardcoded English subtitles.\n\n\nVideo...: H.264/AVC Video\nAudio...:192 kbps, 2 Channel (AAC)\nSource..: Release from Doki\n\n\nCheck out my blog:\nyoushikibimp4encodes.wordpress","torrent":{"xt":"urn:btih:a0f219b923abb78ae9abe34ac3701354f0d567c8","amp;dn":"%5Byoushikibi%5D+Jinrui+wa+Suitai+Shimashita+-+Episode+01+%5B720p%5D+%5BEn","amp;tr":["udp%3A%2F%2Ftracker.openbittorrent.com%3A80","udp%3A%2F%2Fopen.demonii.com%3A1337","udp%3A%2F%2Ftracker.coppersurfer.tk%3A6969","udp%3A%2F%2Fexodus.desync.com%3A6969"],"infoHash":"a0f219b923abb78ae9abe34ac3701354f0d567c8","infoHashBuffer":{"type":"Buffer","data":[160,242,25,185,35,171,183,138,233,171,227,74,195,112,19,84,240,213,103,200]},"announce":[],"urlList":[]}}