{"title":"Natural.Beauties.XXX.DVDRip.XviD-STARLETS","uid":7591950,"size":1466902088,"categoryP":"porn","categoryS":"movies","magnet":"?xt=urn:btih:a926ca95d276f027121702da4e54fe37ccfa7132&amp;dn=Natural.Beauties.XXX.DVDRip.XviD-STARLETS&amp;tr=udp%3A%2F%2Ftracker.openbittorrent.com%3A80&amp;tr=udp%3A%2F%2Fopen.demonii.com%3A1337&amp;tr=udp%3A%2F%2Ftracker.coppersurfer.tk%3A6969&amp;tr=udp%3A%2F%2Fexodus.desync.com%3A6969","seeders":0,"leechers":0,"uploader":"kelvin09","files":2,"time":1346577634,"description":"Natural.Beauties.XXX.DVDRip.XviD-STARLETS\n\n\n\nCover\n &lt;a href=&quot;\nhttp://www.picrak.com/viewer.php?file=31110969999947705367.jpg&quot; rel=&quot;nofollow&quot; target=&quot;_NEW&quot;&gt;\nhttp://www.picrak.com/viewer.php?file=31110969999947705367.jpg&lt;/a&gt;\n\n\nScreens\n\n &lt;a href=&quot;\nhttp://www.picrak.com/viewer.php?file=07692384051731170356.jpg&quot; rel=&quot;nofollow&quot; target=&quot;_NEW&quot;&gt;\nhttp://www.picrak.com/viewer.php?file=07692384051731170356.jpg&lt;/a&gt;\n &lt;a href=&quot;\nhttp://www.picrak.com/viewer.php?file=60914074697801210241.jpg&quot; rel=&quot;nofollow&quot; target=&quot;_NEW&quot;&gt;\nhttp://www.picrak.com/viewer.php?file=60914074697801210241.jpg&lt;/a&gt;\n\n\nVeronica, Krystal Swift, Erin, Conny, Carmen Croft\n\n\n\nNatural Beauties porn A breast lover`s dream come true for real! Cover girl Conny strips down for you, showing off her bald pussy and gorgeous, perfectly shaped jugs! Her man Denson responds by going down on her sweet nether lips and taking her nimble frame doggie style! Curvy blonde Krystal`s tan line gets exposed during some heavy duty breast ballin`! And don`t miss anal lovin` Erin she can`t get started without a good, deep breast massage, then watch that tight ass get busy! ","torrent":{"xt":"urn:btih:a926ca95d276f027121702da4e54fe37ccfa7132","amp;dn":"Natural.Beauties.XXX.DVDRip.XviD-STARLETS","amp;tr":["udp%3A%2F%2Ftracker.openbittorrent.com%3A80","udp%3A%2F%2Fopen.demonii.com%3A1337","udp%3A%2F%2Ftracker.coppersurfer.tk%3A6969","udp%3A%2F%2Fexodus.desync.com%3A6969"],"infoHash":"a926ca95d276f027121702da4e54fe37ccfa7132","infoHashBuffer":{"type":"Buffer","data":[169,38,202,149,210,118,240,39,18,23,2,218,78,84,254,55,204,250,113,50]},"announce":[],"urlList":[]}}