{"title":"Lamb Of God Wrath Tour 2012","uid":7555768,"size":111560175,"categoryP":"audio","categoryS":"music","magnet":"?xt=urn:btih:a9ca868374a715c539e0652b72aa33cbbeff3c83&amp;dn=Lamb+Of+God+Wrath+Tour+2012&amp;tr=udp%3A%2F%2Ftracker.openbittorrent.com%3A80&amp;tr=udp%3A%2F%2Fopen.demonii.com%3A1337&amp;tr=udp%3A%2F%2Ftracker.coppersurfer.tk%3A6969&amp;tr=udp%3A%2F%2Fexodus.desync.com%3A6969","seeders":0,"leechers":0,"uploader":"FernandoFrank","files":14,"time":1345604749,"description":"Audio rip","torrent":{"xt":"urn:btih:a9ca868374a715c539e0652b72aa33cbbeff3c83","amp;dn":"Lamb+Of+God+Wrath+Tour+2012","amp;tr":["udp%3A%2F%2Ftracker.openbittorrent.com%3A80","udp%3A%2F%2Fopen.demonii.com%3A1337","udp%3A%2F%2Ftracker.coppersurfer.tk%3A6969","udp%3A%2F%2Fexodus.desync.com%3A6969"],"infoHash":"a9ca868374a715c539e0652b72aa33cbbeff3c83","infoHashBuffer":{"type":"Buffer","data":[169,202,134,131,116,167,21,197,57,224,101,43,114,170,51,203,190,255,60,131]},"announce":[],"urlList":[]}}