{"title":"Legends.of.Pegasus.v1.0.0.4066.Update-SKIDROW","uid":7570972,"size":19649535,"categoryP":"games","categoryS":"pc","magnet":"?xt=urn:btih:ae73ca93445201555372736cfc94756febce096f&amp;dn=Legends.of.Pegasus.v1.0.0.4066.Update-SKIDROW&amp;tr=udp%3A%2F%2Ftracker.openbittorrent.com%3A80&amp;tr=udp%3A%2F%2Fopen.demonii.com%3A1337&amp;tr=udp%3A%2F%2Ftracker.coppersurfer.tk%3A6969&amp;tr=udp%3A%2F%2Fexodus.desync.com%3A6969","seeders":0,"leechers":0,"uploader":"haloReD","files":-1,"time":1345990231,"description":"Legends of Pegasus v1.0.0.4066 Update\n\n27-08-2012......Release Date &lt;-&gt; Protection...Steam+Serial+Custom\nStrategy...........Game Type &lt;-&gt; Disk(s)......................DOX\n\nRELEASE NOTES\n\nRead changelog.txt for information on updated content!\n\nINSTALL NOTES\n\n1. Unpack release\n2. Run Legends.of.Pegasus.v1.0.0.4066.Update.exe\n3. Install\n4. Copy the cracked content from the SKIDROW folder to the main install\nfolder and overwrite\n5. Play the game\n6. Support the companies, which software you actually enjoy!\n\nADDITIONAL NOTES\n\nUse Launcher.exe, included with the cracked content, for setting the\nlanguage of your choice\n\nYou don't need to have any of the previous updates installed, as this\nupdate is featuring all previous updated content","torrent":{"xt":"urn:btih:ae73ca93445201555372736cfc94756febce096f","amp;dn":"Legends.of.Pegasus.v1.0.0.4066.Update-SKIDROW","amp;tr":["udp%3A%2F%2Ftracker.openbittorrent.com%3A80","udp%3A%2F%2Fopen.demonii.com%3A1337","udp%3A%2F%2Ftracker.coppersurfer.tk%3A6969","udp%3A%2F%2Fexodus.desync.com%3A6969"],"infoHash":"ae73ca93445201555372736cfc94756febce096f","infoHashBuffer":{"type":"Buffer","data":[174,115,202,147,68,82,1,85,83,114,115,108,252,148,117,111,235,206,9,111]},"announce":[],"urlList":[]}}