{"title":"StellarPhoenixWindowsDataRecovery","uid":7434632,"size":6540383,"categoryP":"applications","categoryS":"windows","magnet":"?xt=urn:btih:c12c95ebc63c6aad96207ced64fb427d92db9e7f&amp;dn=StellarPhoenixWindowsDataRecovery&amp;tr=udp%3A%2F%2Ftracker.openbittorrent.com%3A80&amp;tr=udp%3A%2F%2Fopen.demonii.com%3A1337&amp;tr=udp%3A%2F%2Ftracker.coppersurfer.tk%3A6969&amp;tr=udp%3A%2F%2Fexodus.desync.com%3A6969","seeders":0,"leechers":0,"uploader":"marathaempire","files":1,"time":1342037029,"description":"Full version ","torrent":{"xt":"urn:btih:c12c95ebc63c6aad96207ced64fb427d92db9e7f","amp;dn":"StellarPhoenixWindowsDataRecovery","amp;tr":["udp%3A%2F%2Ftracker.openbittorrent.com%3A80","udp%3A%2F%2Fopen.demonii.com%3A1337","udp%3A%2F%2Ftracker.coppersurfer.tk%3A6969","udp%3A%2F%2Fexodus.desync.com%3A6969"],"infoHash":"c12c95ebc63c6aad96207ced64fb427d92db9e7f","infoHashBuffer":{"type":"Buffer","data":[193,44,149,235,198,60,106,173,150,32,124,237,100,251,66,125,146,219,158,127]},"announce":[],"urlList":[]}}