{"title":"18XGirls - Summer Fun With Carine [1080p].wmv","uid":7479970,"size":753228854,"categoryP":"porn","categoryS":"hd___movies","magnet":"?xt=urn:btih:cd5ac7cf13e74238ddafb8b16eea88eff66f52e7&amp;dn=18XGirls+-+Summer+Fun+With+Carine+%5B1080p%5D.wmv&amp;tr=udp%3A%2F%2Ftracker.openbittorrent.com%3A80&amp;tr=udp%3A%2F%2Fopen.demonii.com%3A1337&amp;tr=udp%3A%2F%2Ftracker.coppersurfer.tk%3A6969&amp;tr=udp%3A%2F%2Fexodus.desync.com%3A6969","seeders":0,"leechers":2,"uploader":"C3Porno","files":-1,"time":1343402873,"description":"18XGirls - Summer Fun With Carine [1080p].wmv\n\n2012, Hardcore, Teen, HD, Oral, XXX, Adult\n\n1920 x 1080\n\n00:20:27\n\n718.34 MB \n\nScreens\n &lt;a href=&quot;\nhttp://www.euro-pic.eu/share-7470_501298FE.html&quot; rel=&quot;nofollow&quot; target=&quot;_NEW&quot;&gt;\nhttp://www.euro-pic.eu/share-7470_501298FE.html&lt;/a&gt;\n &lt;a href=&quot;\nhttp://www.euro-pic.eu/share-6953_501298FE.html&quot; rel=&quot;nofollow&quot; target=&quot;_NEW&quot;&gt;\nhttp://www.euro-pic.eu/share-6953_501298FE.html&lt;/a&gt;\n &lt;a href=&quot;\nhttp://www.euro-pic.eu/share-55C0_501298FE.html&quot; rel=&quot;nofollow&quot; target=&quot;_NEW&quot;&gt;\nhttp://www.euro-pic.eu/share-55C0_501298FE.html&lt;/a&gt;\n &lt;a href=&quot;\nhttp://www.euro-pic.eu/share-E0E3_501298FE.html&quot; rel=&quot;nofollow&quot; target=&quot;_NEW&quot;&gt;\nhttp://www.euro-pic.eu/share-E0E3_501298FE.html&lt;/a&gt;\n &lt;a href=&quot;\nhttp://www.euro-pic.eu/share-C5E1_501298FE.html&quot; rel=&quot;nofollow&quot; target=&quot;_NEW&quot;&gt;\nhttp://www.euro-pic.eu/share-C5E1_501298FE.html&lt;/a&gt;\n","torrent":{"xt":"urn:btih:cd5ac7cf13e74238ddafb8b16eea88eff66f52e7","amp;dn":"18XGirls+-+Summer+Fun+With+Carine+%5B1080p%5D.wmv","amp;tr":["udp%3A%2F%2Ftracker.openbittorrent.com%3A80","udp%3A%2F%2Fopen.demonii.com%3A1337","udp%3A%2F%2Ftracker.coppersurfer.tk%3A6969","udp%3A%2F%2Fexodus.desync.com%3A6969"],"infoHash":"cd5ac7cf13e74238ddafb8b16eea88eff66f52e7","infoHashBuffer":{"type":"Buffer","data":[205,90,199,207,19,231,66,56,221,175,184,177,110,234,136,239,246,111,82,231]},"announce":[],"urlList":[]}}