{"title":"BigTitsAtWork - Alexis Ford {Perks of the Job}","uid":7103725,"size":296897961,"categoryP":"porn","categoryS":"movie_clips","magnet":"?xt=urn:btih:d09b7d145fd124c330fe3a9810f6be5a61465234&amp;dn=BigTitsAtWork+-+Alexis+Ford+%7BPerks+of+the+Job%7D&amp;tr=udp%3A%2F%2Ftracker.openbittorrent.com%3A80&amp;tr=udp%3A%2F%2Fopen.demonii.com%3A1337&amp;tr=udp%3A%2F%2Ftracker.coppersurfer.tk%3A6969&amp;tr=udp%3A%2F%2Fexodus.desync.com%3A6969","seeders":0,"leechers":1,"uploader":"Xavier461","files":1,"time":1331789027,"description":"Screenshots\n &lt;a href=&quot;\nhttp://bayimg.com/IannKaadE&quot; rel=&quot;nofollow&quot; target=&quot;_NEW&quot;&gt;\nhttp://bayimg.com/IannKaadE&lt;/a&gt;\n\n\n\nSize: 296897961 bytes (283.14 MiB), duration: 00:33:22, avg.bitrate: 1186 kb/s\nAudio: aac, 48000 Hz, stereo (eng)\nVideo: h264, yuv420p, 854x480, 29.97 fps\n\n\nAlexis' sole responsibility at ZZ corp is to ensure the comfort of the employees, facilitating their transition from stuffy cubicle jobs to the world of private offices complete with concubines. ZZ corp cares about you, and won't let you get stressed out, even if it means tit-fucking you while you're trying to work. ","torrent":{"xt":"urn:btih:d09b7d145fd124c330fe3a9810f6be5a61465234","amp;dn":"BigTitsAtWork+-+Alexis+Ford+%7BPerks+of+the+Job%7D","amp;tr":["udp%3A%2F%2Ftracker.openbittorrent.com%3A80","udp%3A%2F%2Fopen.demonii.com%3A1337","udp%3A%2F%2Ftracker.coppersurfer.tk%3A6969","udp%3A%2F%2Fexodus.desync.com%3A6969"],"infoHash":"d09b7d145fd124c330fe3a9810f6be5a61465234","infoHashBuffer":{"type":"Buffer","data":[208,155,125,20,95,209,36,195,48,254,58,152,16,246,190,90,97,70,82,52]},"announce":[],"urlList":[]}}