{"title":"Coronation Street 5th September 2012","uid":7603284,"size":249231706,"categoryP":"video","categoryS":"tv_shows","magnet":"?xt=urn:btih:d43f9457b70a98ffe4aab0e6078752c15caec8ce&amp;dn=Coronation+Street+5th+September+2012&amp;tr=udp%3A%2F%2Ftracker.openbittorrent.com%3A80&amp;tr=udp%3A%2F%2Fopen.demonii.com%3A1337&amp;tr=udp%3A%2F%2Ftracker.coppersurfer.tk%3A6969&amp;tr=udp%3A%2F%2Fexodus.desync.com%3A6969","seeders":0,"leechers":0,"uploader":"albiondean","files":1,"time":1346879851,"description":"Coronation Street 5th September 2012","torrent":{"xt":"urn:btih:d43f9457b70a98ffe4aab0e6078752c15caec8ce","amp;dn":"Coronation+Street+5th+September+2012","amp;tr":["udp%3A%2F%2Ftracker.openbittorrent.com%3A80","udp%3A%2F%2Fopen.demonii.com%3A1337","udp%3A%2F%2Ftracker.coppersurfer.tk%3A6969","udp%3A%2F%2Fexodus.desync.com%3A6969"],"infoHash":"d43f9457b70a98ffe4aab0e6078752c15caec8ce","infoHashBuffer":{"type":"Buffer","data":[212,63,148,87,183,10,152,255,228,170,176,230,7,135,82,193,92,174,200,206]},"announce":[],"urlList":[]}}