{"title":"Interview.With.A.Hitman.BDRiP.XViD-TASTE","uid":7590046,"size":736698644,"categoryP":"video","categoryS":"movies","magnet":"?xt=urn:btih:d96e6065a54d77c4dad7f6ed1b29e1bcd0e94302&amp;dn=Interview.With.A.Hitman.BDRiP.XViD-TASTE&amp;tr=udp%3A%2F%2Ftracker.openbittorrent.com%3A80&amp;tr=udp%3A%2F%2Fopen.demonii.com%3A1337&amp;tr=udp%3A%2F%2Ftracker.coppersurfer.tk%3A6969&amp;tr=udp%3A%2F%2Fexodus.desync.com%3A6969","seeders":0,"leechers":0,"uploader":"UltraTorrents","files":2,"time":1346514670,"description":"INFO, POSTER &amp; TRAILER\n                                                 &lt;a href=&quot;\nhttp://www.sharepixon.net/movies/interview-with-a-hitman&quot; rel=&quot;nofollow&quot; target=&quot;_NEW&quot;&gt;\nhttp://www.sharepixon.net/movies/interview-with-a-hitman&lt;/a&gt;\n\n[url]http://www.sharepixon.net/movies/interview-with-a-hitman[/url]\n\n\nSCREENSHOTS:\n                                                &lt;a href=&quot;\nhttp://img.sharepixon.net/?v=intervhsh.png&quot; rel=&quot;nofollow&quot; target=&quot;_NEW&quot;&gt;\nhttp://img.sharepixon.net/?v=intervhsh.png&lt;/a&gt; &lt;a href=&quot;\nhttp://img.sharepixon.net/?v=interveee.png&quot; rel=&quot;nofollow&quot; target=&quot;_NEW&quot;&gt;\nhttp://img.sharepixon.net/?v=interveee.png&lt;/a&gt;\n\n[url]http://img.sharepixon.net/?v=intervhsh.png[/url]\t\n[url]http://img.sharepixon.net/?v=interveee.png[/url]\t\n\t\n\t\t","torrent":{"xt":"urn:btih:d96e6065a54d77c4dad7f6ed1b29e1bcd0e94302","amp;dn":"Interview.With.A.Hitman.BDRiP.XViD-TASTE","amp;tr":["udp%3A%2F%2Ftracker.openbittorrent.com%3A80","udp%3A%2F%2Fopen.demonii.com%3A1337","udp%3A%2F%2Ftracker.coppersurfer.tk%3A6969","udp%3A%2F%2Fexodus.desync.com%3A6969"],"infoHash":"d96e6065a54d77c4dad7f6ed1b29e1bcd0e94302","infoHashBuffer":{"type":"Buffer","data":[217,110,96,101,165,77,119,196,218,215,246,237,27,41,225,188,208,233,67,2]},"announce":[],"urlList":[]}}