{"title":"Gorillaz-Feel_Good_Inc__Stanton_Warriors_Mix_(WAX005)-Promo-VLS-","uid":7444827,"size":9867633,"categoryP":"audio","categoryS":"music","magnet":"?xt=urn:btih:ddd9bf5ea651e07489136395e3db45999f39a8fe&amp;dn=Gorillaz-Feel_Good_Inc__Stanton_Warriors_Mix_%28WAX005%29-Promo-VLS-&amp;tr=udp%3A%2F%2Ftracker.openbittorrent.com%3A80&amp;tr=udp%3A%2F%2Fopen.demonii.com%3A1337&amp;tr=udp%3A%2F%2Ftracker.coppersurfer.tk%3A6969&amp;tr=udp%3A%2F%2Fexodus.desync.com%3A6969","seeders":0,"leechers":1,"uploader":null,"files":2,"time":1342336309,"description":"Gorillaz-Feel_Good_Inc__Stanton_Warriors_Mix_(WAX005)-Promo-VLS-","torrent":{"xt":"urn:btih:ddd9bf5ea651e07489136395e3db45999f39a8fe","amp;dn":"Gorillaz-Feel_Good_Inc__Stanton_Warriors_Mix_%28WAX005%29-Promo-VLS-","amp;tr":["udp%3A%2F%2Ftracker.openbittorrent.com%3A80","udp%3A%2F%2Fopen.demonii.com%3A1337","udp%3A%2F%2Ftracker.coppersurfer.tk%3A6969","udp%3A%2F%2Fexodus.desync.com%3A6969"],"infoHash":"ddd9bf5ea651e07489136395e3db45999f39a8fe","infoHashBuffer":{"type":"Buffer","data":[221,217,191,94,166,81,224,116,137,19,99,149,227,219,69,153,159,57,168,254]},"announce":[],"urlList":[]}}