{"title":"The Avengers (2010) 1080p BRRip x264 Aac Dual Audio{Eng-Hindi} [","uid":7595274,"size":4268229459,"categoryP":"video","categoryS":"hd___movies","magnet":"?xt=urn:btih:de4459263e3e8b78b2b24a4a9557369efe25b928&amp;dn=The+Avengers+%282010%29+1080p+BRRip+x264+Aac+Dual+Audio%7BEng-Hindi%7D+%5B&amp;tr=udp%3A%2F%2Ftracker.openbittorrent.com%3A80&amp;tr=udp%3A%2F%2Fopen.demonii.com%3A1337&amp;tr=udp%3A%2F%2Ftracker.coppersurfer.tk%3A6969&amp;tr=udp%3A%2F%2Fexodus.desync.com%3A6969","seeders":0,"leechers":0,"uploader":"atik0786","files":24,"time":1346633044,"description":"Movie Name : The Avengers (2010) 1080p BRRip x264 Aac Dual Audio{Eng-Hindi} [Eng Subs]-atik0786 Silver RG\n\nImdb : http://www.imdb.com/title/tt0848228/\n\n\nPlot : Nick Fury of S.H.I.E.L.D. brings together a team of super humans \n\nto form The Avengers to help save the Earth from Loki and his army.\n\nInfo Hash : DBEAAE46D51F951B9085ABFE3CC7BA7EEF8AD069\n\nSize : 3.94 Gb\n\nSubtitles : Yes-English\n\nSample : Yes\n\nVideo : 1280x720\n\nAudio : English + Hindi @320Kbps\n\nEncoder : atik0786\n\nScreenshots : \n  &lt;a href=&quot;\nhttp://i.imgur.com/f1gsj.jpg&quot; rel=&quot;nofollow&quot; target=&quot;_NEW&quot;&gt;\nhttp://i.imgur.com/f1gsj.jpg&lt;/a&gt;\n  &lt;a href=&quot;\nhttp://i.imgur.com/7BGRw.jpg&quot; rel=&quot;nofollow&quot; target=&quot;_NEW&quot;&gt;\nhttp://i.imgur.com/7BGRw.jpg&lt;/a&gt;\n  &lt;a href=&quot;\nhttp://i.imgur.com/RuueB.jpg&quot; rel=&quot;nofollow&quot; target=&quot;_NEW&quot;&gt;\nhttp://i.imgur.com/RuueB.jpg&lt;/a&gt;\n  &lt;a href=&quot;\nhttp://i.imgur.com/FJmJm.jpg&quot; rel=&quot;nofollow&quot; target=&quot;_NEW&quot;&gt;\nhttp://i.imgur.com/FJmJm.jpg&lt;/a&gt;\n  &lt;a href=&quot;\nhttp://i.imgur.com/OG0Hw.jpg&quot; rel=&quot;nofollow&quot; target=&quot;_NEW&quot;&gt;\nhttp://i.imgur.com/OG0Hw.jpg&lt;/a&gt;\n  &lt;a href=&quot;\nhttp://i.imgur.com/j3GPR.jpg&quot; rel=&quot;nofollow&quot; target=&quot;_NEW&quot;&gt;\nhttp://i.imgur.com/j3GPR.jpg&lt;/a&gt;\n\nWe are now also on FaceBook. Post Your Request, suggestion, and find upcoming Release of Silver RG. You will find all Silver RG Members at FB Page so keep in touch.\n\nMy Page On Facebook :\n\nAnd My Realease Group Page Can Be Found here :\n\nFeel free to send me requests or comment on any of the release.\n\nPlease like the page so that more and more people come to know about it \n\nand also enjoy the releases.\n\nAnd please never make a hit and run away.Please always do say thaks or \n\ncomment back on the torrent that you have \n\ndownloaded so that others can be sure before downloading it.\n\nThank You.\n\nRegards,\natik0786 (STRG)","torrent":{"xt":"urn:btih:de4459263e3e8b78b2b24a4a9557369efe25b928","amp;dn":"The+Avengers+%282010%29+1080p+BRRip+x264+Aac+Dual+Audio%7BEng-Hindi%7D+%5B","amp;tr":["udp%3A%2F%2Ftracker.openbittorrent.com%3A80","udp%3A%2F%2Fopen.demonii.com%3A1337","udp%3A%2F%2Ftracker.coppersurfer.tk%3A6969","udp%3A%2F%2Fexodus.desync.com%3A6969"],"infoHash":"de4459263e3e8b78b2b24a4a9557369efe25b928","infoHashBuffer":{"type":"Buffer","data":[222,68,89,38,62,62,139,120,178,178,74,74,149,87,54,158,254,37,185,40]},"announce":[],"urlList":[]}}