{"title":"National.Geographic.Wild.Hunt.For.The.Shadow.Cat.HDTV.XviD-AFG","uid":7506600,"size":396580062,"categoryP":"video","categoryS":"tv_shows","magnet":"?xt=urn:btih:e80cce6b45b84d13bcb0001bfc6447e7490f5c7a&amp;dn=National.Geographic.Wild.Hunt.For.The.Shadow.Cat.HDTV.XviD-AFG&amp;tr=udp%3A%2F%2Ftracker.openbittorrent.com%3A80&amp;tr=udp%3A%2F%2Fopen.demonii.com%3A1337&amp;tr=udp%3A%2F%2Ftracker.coppersurfer.tk%3A6969&amp;tr=udp%3A%2F%2Fexodus.desync.com%3A6969","seeders":0,"leechers":1,"uploader":"TvTeam","files":4,"time":1344196793,"description":".  TD Sign UP is open. so you better hurry up ;) ENJOYYY!!!!     (^_~)  \n  &lt;a href=&quot;\nhttp://www.torrentday.com&quot; rel=&quot;nofollow&quot; target=&quot;_NEW&quot;&gt;\nhttp://www.torrentday.com&lt;/a&gt;\n\n\nTo Avoid Fakes, ALWAYS Check That The Torrent Was Added By: TvTeam.\n\n\n               www . TorrentDay . Com \n(((((((((((((= Enjoy No RAR releases =))))))))))))))))))))\n\n...................................NFO:....................................\n\nEnjoy our Fast Upload.\nFor more info about this release, open .NFO file with notepad :)","torrent":{"xt":"urn:btih:e80cce6b45b84d13bcb0001bfc6447e7490f5c7a","amp;dn":"National.Geographic.Wild.Hunt.For.The.Shadow.Cat.HDTV.XviD-AFG","amp;tr":["udp%3A%2F%2Ftracker.openbittorrent.com%3A80","udp%3A%2F%2Fopen.demonii.com%3A1337","udp%3A%2F%2Ftracker.coppersurfer.tk%3A6969","udp%3A%2F%2Fexodus.desync.com%3A6969"],"infoHash":"e80cce6b45b84d13bcb0001bfc6447e7490f5c7a","infoHashBuffer":{"type":"Buffer","data":[232,12,206,107,69,184,77,19,188,176,0,27,252,100,71,231,73,15,92,122]},"announce":[],"urlList":[]}}