{"title":"Third Doctor - Inferno (rus sub)","uid":7610382,"size":2497431698,"categoryP":"video","categoryS":"tv_shows","magnet":"?xt=urn:btih:f2a72c2c07d5cc1f93a8abc8bdf5e542da707400&amp;dn=Third+Doctor+-+Inferno+%28rus+sub%29&amp;tr=udp%3A%2F%2Ftracker.openbittorrent.com%3A80&amp;tr=udp%3A%2F%2Fopen.demonii.com%3A1337&amp;tr=udp%3A%2F%2Ftracker.coppersurfer.tk%3A6969&amp;tr=udp%3A%2F%2Fexodus.desync.com%3A6969","seeders":0,"leechers":0,"uploader":"miamiara","files":14,"time":1347047453,"description":"Doctor who, third doctor era - Inferno (7 ep, eng, rus subs)","torrent":{"xt":"urn:btih:f2a72c2c07d5cc1f93a8abc8bdf5e542da707400","amp;dn":"Third+Doctor+-+Inferno+%28rus+sub%29","amp;tr":["udp%3A%2F%2Ftracker.openbittorrent.com%3A80","udp%3A%2F%2Fopen.demonii.com%3A1337","udp%3A%2F%2Ftracker.coppersurfer.tk%3A6969","udp%3A%2F%2Fexodus.desync.com%3A6969"],"infoHash":"f2a72c2c07d5cc1f93a8abc8bdf5e542da707400","infoHashBuffer":{"type":"Buffer","data":[242,167,44,44,7,213,204,31,147,168,171,200,189,245,229,66,218,112,116,0]},"announce":[],"urlList":[]}}